CHANGES.rst
LICENSE.txt
MANIFEST.in
README.md
setup.py
cmsplugin_twcarousel.egg-info/PKG-INFO
cmsplugin_twcarousel.egg-info/SOURCES.txt
cmsplugin_twcarousel.egg-info/dependency_links.txt
cmsplugin_twcarousel.egg-info/not-zip-safe
cmsplugin_twcarousel.egg-info/top_level.txt
twcarousel/__init__.py
twcarousel/admin.py
twcarousel/cms_plugins.py
twcarousel/models.py
twcarousel/static/css/bootstrap.css
twcarousel/static/js/bootstrap.js
twcarousel/templates/twcarousel/carousel.html