Metadata-Version: 1.1
Name: cmsplugin-twcarousel
Version: 0.1c0
Summary: A Twitter Bootstrap Carousel plugin for Django CMS.
Home-page: https://github.com/kevwilde/cmsplugin-twcarousel
Author: Kevin Van Wilder
Author-email: kevin@van-wilder.be
License: BSD
Platform: UNKNOWN
Classifier: Development Status :: 3 - Alpha
Classifier: Environment :: Web Environment
Classifier: Framework :: Django
Classifier: Intended Audience :: Developers
Classifier: License :: OSI Approved :: BSD License
Classifier: Operating System :: MacOS :: MacOS X
Classifier: Operating System :: Microsoft :: Windows
Classifier: Operating System :: POSIX
Classifier: Programming Language :: Python
Classifier: Topic :: Internet :: WWW/HTTP :: Dynamic Content
Classifier: Topic :: Software Development :: Libraries
